MANIFEST.in
README.rst
setup.py
tgext/__init__.py
tgext.utils.egg-info/PKG-INFO
tgext.utils.egg-info/SOURCES.txt
tgext.utils.egg-info/dependency_links.txt
tgext.utils.egg-info/entry_points.txt
tgext.utils.egg-info/namespace_packages.txt
tgext.utils.egg-info/not-zip-safe
tgext.utils.egg-info/requires.txt
tgext.utils.egg-info/top_level.txt
tgext/utils/__init__.py
tgext/utils/ajax.py
tgext/utils/csrf.py
tgext/utils/meta.py
tgext/utils/slug.py
tgext/utils/storage.py