Metadata-Version: 1.0
Name: tgext.utils
Version: 0.0.3
Summary: Collection of utilities for TurboGears2
Home-page: https://github.com/amol-/tgext.utils
Author: Alessandro Molina
Author-email: amol@turbogears.org
License: MIT
Keywords: turbogears2.extension
Platform: UNKNOWN
